fastopendata_client/__init__.py
fastopendata_client/cli_entry.py
fastopendata_client/client.py
fastopendata_client/config.toml
fastopendata_client-0.0.33.dist-info/METADATA
fastopendata_client-0.0.33.dist-info/WHEEL
fastopendata_client-0.0.33.dist-info/entry_points.txt
fastopendata_client-0.0.33.dist-info/licenses/LICENSE
fastopendata_client-0.0.33.dist-info/RECORD
