Metadata-Version: 2.1
Name: fastopendata_client
Version: 0.0.33
Summary: Client for the FastOpenData API service
Project-URL: Homepage, https://github.com/zacernst/fastopendata
Project-URL: Bug Tracker, https://github.com/zacernst/fastopendata/issues
Author-email: Zachary Ernst <zac@fastopendata.com>
License-File: LICENSE
Classifier: License :: OSI Approved :: MIT License
Classifier: Operating System :: OS Independent
Classifier: Programming Language :: Python :: 3
Requires-Python: >=3.8
Requires-Dist: anyio==3.7.1
Requires-Dist: bandit==1.7.5
Requires-Dist: bleach==6.0.0
Requires-Dist: certifi==2023.5.7
Requires-Dist: charset-normalizer==3.1.0
Requires-Dist: click==8.1.5
Requires-Dist: distlib==0.3.6
Requires-Dist: docutils==0.20.1
Requires-Dist: editables==0.4
Requires-Dist: exceptiongroup==1.1.2
Requires-Dist: filelock==3.12.2
Requires-Dist: gitdb==4.0.10
Requires-Dist: gitpython==3.1.31
Requires-Dist: h11==0.14.0
Requires-Dist: hatch==1.7.0
Requires-Dist: hatchling==1.18.0
Requires-Dist: httpcore==0.17.3
Requires-Dist: httpx==0.24.1
Requires-Dist: hyperlink==21.0.0
Requires-Dist: idna==3.4
Requires-Dist: importlib-metadata==6.8.0
Requires-Dist: jaraco-classes==3.3.0
Requires-Dist: keyring==24.2.0
Requires-Dist: markdown-it-py==3.0.0
Requires-Dist: mdurl==0.1.2
Requires-Dist: more-itertools==9.1.0
Requires-Dist: numpy==1.25.0
Requires-Dist: packaging==23.1
Requires-Dist: pandas==2.0.3
Requires-Dist: pathspec==0.11.1
Requires-Dist: pbr==5.11.1
Requires-Dist: pexpect==4.8.0
Requires-Dist: pkginfo==1.9.6
Requires-Dist: platformdirs==3.8.1
Requires-Dist: pluggy==1.2.0
Requires-Dist: ptyprocess==0.7.0
Requires-Dist: pyfiglet==0.8.post1
Requires-Dist: pygments==2.15.1
Requires-Dist: pyperclip==1.8.2
Requires-Dist: python-dateutil==2.8.2
Requires-Dist: pytz==2023.3
Requires-Dist: pyyaml==6.0
Requires-Dist: random-address==1.1.1
Requires-Dist: readme-renderer==40.0
Requires-Dist: requests-toolbelt==1.0.0
Requires-Dist: requests==2.31.0
Requires-Dist: rfc3986==2.0.0
Requires-Dist: rich==13.4.2
Requires-Dist: shellingham==1.5.0.post1
Requires-Dist: six==1.16.0
Requires-Dist: smmap==5.0.0
Requires-Dist: sniffio==1.3.0
Requires-Dist: stevedore==5.1.0
Requires-Dist: toml==0.10.2
Requires-Dist: tomli-w==1.0.0
Requires-Dist: tomli==2.0.1
Requires-Dist: tomlkit==0.11.8
Requires-Dist: tqdm==4.65.0
Requires-Dist: trove-classifiers==2023.7.6
Requires-Dist: twine==4.0.2
Requires-Dist: tzdata==2023.3
Requires-Dist: urllib3==2.0.3
Requires-Dist: userpath==1.8.0
Requires-Dist: virtualenv==20.23.1
Requires-Dist: webencodings==0.5.1
Requires-Dist: zipp==3.16.1
